AUTHORS
CHANGELOG.txt
DESCRIPTION
LICENSE
MANIFEST.in
setup.py
django_multilingual_initiatives.egg-info/PKG-INFO
django_multilingual_initiatives.egg-info/SOURCES.txt
django_multilingual_initiatives.egg-info/dependency_links.txt
django_multilingual_initiatives.egg-info/requires.txt
django_multilingual_initiatives.egg-info/top_level.txt
multilingual_initiatives/__init__.py
multilingual_initiatives/admin.py
multilingual_initiatives/cms_plugins.py
multilingual_initiatives/models.py
multilingual_initiatives/settings.py
multilingual_initiatives/migrations/0001_initial.py
multilingual_initiatives/migrations/0002_auto__add_initiativepersonrole.py
multilingual_initiatives/migrations/0003_rename_translations.py
multilingual_initiatives/migrations/__init__.py
multilingual_initiatives/templates/multilingual_initiatives/initiative_plugin.html
multilingual_initiatives/tests/__init__.py
multilingual_initiatives/tests/factories.py
multilingual_initiatives/tests/models_tests.py
multilingual_initiatives/tests/runtests.py
multilingual_initiatives/tests/south_settings.py
multilingual_initiatives/tests/test_settings.py
multilingual_initiatives/tests/urls.py
multilingual_initiatives/tests/test_app/__init__.py
multilingual_initiatives/tests/test_app/models.py
multilingual_initiatives/tests/test_app/urls.py
multilingual_initiatives/tests/test_app/templates/base.html
multilingual_initiatives/tests/test_app/templates/standard.html