Metadata-Version: 1.0
Name: django-multilingual-initiatives
Version: 1.0
Summary: An app for showing localized versions of initiatives. E.g. as plugin in a blog
